{
  "nodes": [
    {
      "id": "node_.ai",
      "name": ".ai",
      "path": ".ai",
      "type": "directory",
      "size_raw": 18208,
      "eff": 82
    },
    {
      "id": "node_.ai/AGNOSTIC-ORCH",
      "name": "AGNOSTIC-ORCH",
      "path": ".ai/AGNOSTIC-ORCH",
      "type": "directory",
      "size_raw": 6649,
      "eff": 86
    },
    {
      "id": "node_.ai/ARCHIVE",
      "name": "ARCHIVE",
      "path": ".ai/ARCHIVE",
      "type": "directory",
      "size_raw": 0,
      "eff": 100
    },
    {
      "id": "node_.ai/DECISIONS",
      "name": "DECISIONS",
      "path": ".ai/DECISIONS",
      "type": "directory",
      "size_raw": 1387,
      "eff": 88
    },
    {
      "id": "node_.ai/EVIDENCE",
      "name": "EVIDENCE",
      "path": ".ai/EVIDENCE",
      "type": "data",
      "size_raw": 7025,
      "eff": 87
    },
    {
      "id": "node_.ai/FEDERATION",
      "name": "FEDERATION",
      "path": ".ai/FEDERATION",
      "type": "directory",
      "size_raw": 700,
      "eff": 87
    },
    {
      "id": "node_.ai/FEDERATION_TEMPLATE",
      "name": "FEDERATION_TEMPLATE",
      "path": ".ai/FEDERATION_TEMPLATE",
      "type": "directory",
      "size_raw": 2678,
      "eff": 81
    },
    {
      "id": "node_.ai/SAMPLES",
      "name": "SAMPLES",
      "path": ".ai/SAMPLES",
      "type": "sample",
      "size_raw": 48063,
      "eff": 84
    },
    {
      "id": "node_.ai/SKILLS",
      "name": "SKILLS",
      "path": ".ai/SKILLS",
      "type": "directory",
      "size_raw": 789,
      "eff": 85
    },
    {
      "id": "node_.ai/SKILLSETS",
      "name": "SKILLSETS",
      "path": ".ai/SKILLSETS",
      "type": "directory",
      "size_raw": 1370,
      "eff": 84
    },
    {
      "id": "node_.ai/STATE",
      "name": "STATE",
      "path": ".ai/STATE",
      "type": "data",
      "size_raw": 266,
      "eff": 91
    },
    {
      "id": "node_.ai/STREAMS",
      "name": "STREAMS",
      "path": ".ai/STREAMS",
      "type": "directory",
      "size_raw": 7926,
      "eff": 81
    },
    {
      "id": "node_.ai/TASKS",
      "name": "TASKS",
      "path": ".ai/TASKS",
      "type": "directory",
      "size_raw": 179,
      "eff": 89
    },
    {
      "id": "node_.ai/tools",
      "name": "tools",
      "path": ".ai/tools",
      "type": "tool_py",
      "size_raw": 81909,
      "eff": 75
    },
    {
      "id": "node_.ai/AGNOSTIC-ORCH/knowledge",
      "name": "knowledge",
      "path": ".ai/AGNOSTIC-ORCH/knowledge",
      "type": "directory",
      "size_raw": 42954,
      "eff": 86
    },
    {
      "id": "node_.ai/ARCHIVE/summaries",
      "name": "summaries",
      "path": ".ai/ARCHIVE/summaries",
      "type": "directory",
      "size_raw": 290,
      "eff": 84
    },
    {
      "id": "node_.ai/EVIDENCE/federation",
      "name": "federation",
      "path": ".ai/EVIDENCE/federation",
      "type": "data",
      "size_raw": 257,
      "eff": 90
    },
    {
      "id": "node_.ai/EVIDENCE/research_reports",
      "name": "research_reports",
      "path": ".ai/EVIDENCE/research_reports",
      "type": "data",
      "size_raw": 1308,
      "eff": 87
    },
    {
      "id": "node_.ai/SAMPLES/node_tools",
      "name": "node_tools",
      "path": ".ai/SAMPLES/node_tools",
      "type": "sample",
      "size_raw": 1387,
      "eff": 79
    },
    {
      "id": "node_.ai/SAMPLES/SKILLS",
      "name": "SKILLS",
      "path": ".ai/SAMPLES/SKILLS",
      "type": "sample",
      "size_raw": 13577,
      "eff": 86
    },
    {
      "id": "node_.ai/SAMPLES/SKILLSETS",
      "name": "SKILLSETS",
      "path": ".ai/SAMPLES/SKILLSETS",
      "type": "sample",
      "size_raw": 1302,
      "eff": 74
    },
    {
      "id": "node_.ai/SKILLS/_template",
      "name": "_template",
      "path": ".ai/SKILLS/_template",
      "type": "directory",
      "size_raw": 560,
      "eff": 88
    },
    {
      "id": "node_.ai/STREAMS/20260301",
      "name": "20260301",
      "path": ".ai/STREAMS/20260301",
      "type": "directory",
      "size_raw": 900,
      "eff": 88
    },
    {
      "id": "node_.ai/STREAMS/_config",
      "name": "_config",
      "path": ".ai/STREAMS/_config",
      "type": "directory",
      "size_raw": 200,
      "eff": 76
    },
    {
      "id": "node_.ai/STREAMS/20260301/CHUNK_01",
      "name": "CHUNK_01",
      "path": ".ai/STREAMS/20260301/CHUNK_01",
      "type": "directory",
      "size_raw": 693,
      "eff": 82
    },
    {
      "id": "node_.ai/STREAMS/20260301/INTENT_SYNC",
      "name": "INTENT_SYNC",
      "path": ".ai/STREAMS/20260301/INTENT_SYNC",
      "type": "directory",
      "size_raw": 863,
      "eff": 79
    },
    {
      "id": "node_.ai/tools/__pycache__",
      "name": "__pycache__",
      "path": ".ai/tools/__pycache__",
      "type": "tool_node",
      "size_raw": 5869,
      "eff": 100
    },
    {
      "id": "node_external_repos",
      "name": "external_repos",
      "path": "external_repos",
      "type": "directory",
      "size_raw": 796,
      "eff": 85
    },
    {
      "id": "node_external_repos/repo_alpha",
      "name": "repo_alpha",
      "path": "external_repos/repo_alpha",
      "type": "directory",
      "size_raw": 0,
      "eff": 100
    },
    {
      "id": "node_external_repos/repo_beta",
      "name": "repo_beta",
      "path": "external_repos/repo_beta",
      "type": "directory",
      "size_raw": 0,
      "eff": 100
    },
    {
      "id": "node_external_repos/repo_alpha/.ai",
      "name": ".ai",
      "path": "external_repos/repo_alpha/.ai",
      "type": "directory",
      "size_raw": 0,
      "eff": 100
    },
    {
      "id": "node_external_repos/repo_alpha/.ai/EVIDENCE",
      "name": "EVIDENCE",
      "path": "external_repos/repo_alpha/.ai/EVIDENCE",
      "type": "directory",
      "size_raw": 310,
      "eff": 86
    },
    {
      "id": "node_external_repos/repo_alpha/.ai/FEDERATION",
      "name": "FEDERATION",
      "path": "external_repos/repo_alpha/.ai/FEDERATION",
      "type": "directory",
      "size_raw": 365,
      "eff": 88
    },
    {
      "id": "node_external_repos/repo_alpha/.ai/STATE",
      "name": "STATE",
      "path": "external_repos/repo_alpha/.ai/STATE",
      "type": "directory",
      "size_raw": 184,
      "eff": 91
    },
    {
      "id": "node_external_repos/repo_beta/.ai",
      "name": ".ai",
      "path": "external_repos/repo_beta/.ai",
      "type": "directory",
      "size_raw": 0,
      "eff": 100
    },
    {
      "id": "node_external_repos/repo_beta/.ai/EVIDENCE",
      "name": "EVIDENCE",
      "path": "external_repos/repo_beta/.ai/EVIDENCE",
      "type": "directory",
      "size_raw": 313,
      "eff": 86
    },
    {
      "id": "node_external_repos/repo_beta/.ai/FEDERATION",
      "name": "FEDERATION",
      "path": "external_repos/repo_beta/.ai/FEDERATION",
      "type": "directory",
      "size_raw": 367,
      "eff": 88
    },
    {
      "id": "node_external_repos/repo_beta/.ai/STATE",
      "name": "STATE",
      "path": "external_repos/repo_beta/.ai/STATE",
      "type": "directory",
      "size_raw": 183,
      "eff": 91
    },
    {
      "id": "node_TEMP",
      "name": "TEMP",
      "path": "TEMP",
      "type": "directory",
      "size_raw": 1031,
      "eff": 93
    },
    {
      "id": "node_TEMP/test_projects",
      "name": "test_projects",
      "path": "TEMP/test_projects",
      "type": "directory",
      "size_raw": 0,
      "eff": 100
    },
    {
      "id": "node_TEMP/test_projects/test_node",
      "name": "test_node",
      "path": "TEMP/test_projects/test_node",
      "type": "directory",
      "size_raw": 0,
      "eff": 100
    },
    {
      "id": "node_TEMP/test_projects/test_py",
      "name": "test_py",
      "path": "TEMP/test_projects/test_py",
      "type": "directory",
      "size_raw": 24,
      "eff": 86
    },
    {
      "id": "node_TEMP/test_projects/test_py/.ai",
      "name": ".ai",
      "path": "TEMP/test_projects/test_py/.ai",
      "type": "directory",
      "size_raw": 59,
      "eff": 85
    },
    {
      "id": "node_TEMP/test_projects/test_py/src",
      "name": "src",
      "path": "TEMP/test_projects/test_py/src",
      "type": "directory",
      "size_raw": 0,
      "eff": 100
    },
    {
      "id": "node_TEMP/test_projects/test_py/tests",
      "name": "tests",
      "path": "TEMP/test_projects/test_py/tests",
      "type": "directory",
      "size_raw": 0,
      "eff": 100
    }
  ],
  "links": [
    {
      "source": "node_.ai",
      "target": "node_.ai/AGNOSTIC-ORCH",
      "type": "nesting"
    },
    {
      "source": "node_.ai",
      "target": "node_.ai/ARCHIVE",
      "type": "nesting"
    },
    {
      "source": "node_.ai",
      "target": "node_.ai/DECISIONS",
      "type": "nesting"
    },
    {
      "source": "node_.ai",
      "target": "node_.ai/EVIDENCE",
      "type": "nesting"
    },
    {
      "source": "node_.ai",
      "target": "node_.ai/FEDERATION",
      "type": "nesting"
    },
    {
      "source": "node_.ai",
      "target": "node_.ai/FEDERATION_TEMPLATE",
      "type": "nesting"
    },
    {
      "source": "node_.ai",
      "target": "node_.ai/SAMPLES",
      "type": "nesting"
    },
    {
      "source": "node_.ai",
      "target": "node_.ai/SKILLS",
      "type": "nesting"
    },
    {
      "source": "node_.ai",
      "target": "node_.ai/SKILLSETS",
      "type": "nesting"
    },
    {
      "source": "node_.ai",
      "target": "node_.ai/STATE",
      "type": "nesting"
    },
    {
      "source": "node_.ai",
      "target": "node_.ai/STREAMS",
      "type": "nesting"
    },
    {
      "source": "node_.ai",
      "target": "node_.ai/TASKS",
      "type": "nesting"
    },
    {
      "source": "node_.ai",
      "target": "node_.ai/tools",
      "type": "nesting"
    },
    {
      "source": "node_.ai/AGNOSTIC-ORCH",
      "target": "node_.ai/AGNOSTIC-ORCH/knowledge",
      "type": "nesting"
    },
    {
      "source": "node_.ai/ARCHIVE",
      "target": "node_.ai/ARCHIVE/summaries",
      "type": "nesting"
    },
    {
      "source": "node_.ai/EVIDENCE",
      "target": "node_.ai/EVIDENCE/federation",
      "type": "nesting"
    },
    {
      "source": "node_.ai/EVIDENCE",
      "target": "node_.ai/EVIDENCE/research_reports",
      "type": "nesting"
    },
    {
      "source": "node_.ai/SAMPLES",
      "target": "node_.ai/SAMPLES/node_tools",
      "type": "nesting"
    },
    {
      "source": "node_.ai/SAMPLES",
      "target": "node_.ai/SAMPLES/SKILLS",
      "type": "nesting"
    },
    {
      "source": "node_.ai/SAMPLES",
      "target": "node_.ai/SAMPLES/SKILLSETS",
      "type": "nesting"
    },
    {
      "source": "node_.ai/SKILLS",
      "target": "node_.ai/SKILLS/_template",
      "type": "nesting"
    },
    {
      "source": "node_.ai/STREAMS",
      "target": "node_.ai/STREAMS/20260301",
      "type": "nesting"
    },
    {
      "source": "node_.ai/STREAMS",
      "target": "node_.ai/STREAMS/_config",
      "type": "nesting"
    },
    {
      "source": "node_.ai/STREAMS/20260301",
      "target": "node_.ai/STREAMS/20260301/CHUNK_01",
      "type": "nesting"
    },
    {
      "source": "node_.ai/STREAMS/20260301",
      "target": "node_.ai/STREAMS/20260301/INTENT_SYNC",
      "type": "nesting"
    },
    {
      "source": "node_external_repos",
      "target": "node_external_repos/repo_alpha",
      "type": "nesting"
    },
    {
      "source": "node_external_repos",
      "target": "node_external_repos/repo_beta",
      "type": "nesting"
    },
    {
      "source": "node_external_repos/repo_alpha",
      "target": "node_external_repos/repo_alpha/.ai",
      "type": "nesting"
    },
    {
      "source": "node_external_repos/repo_beta",
      "target": "node_external_repos/repo_beta/.ai",
      "type": "nesting"
    },
    {
      "source": "node_external_repos/repo_alpha/.ai",
      "target": "node_external_repos/repo_alpha/.ai/EVIDENCE",
      "type": "nesting"
    },
    {
      "source": "node_external_repos/repo_alpha/.ai",
      "target": "node_external_repos/repo_alpha/.ai/FEDERATION",
      "type": "nesting"
    },
    {
      "source": "node_external_repos/repo_alpha/.ai",
      "target": "node_external_repos/repo_alpha/.ai/STATE",
      "type": "nesting"
    },
    {
      "source": "node_external_repos/repo_beta/.ai",
      "target": "node_external_repos/repo_beta/.ai/EVIDENCE",
      "type": "nesting"
    },
    {
      "source": "node_external_repos/repo_beta/.ai",
      "target": "node_external_repos/repo_beta/.ai/FEDERATION",
      "type": "nesting"
    },
    {
      "source": "node_external_repos/repo_beta/.ai",
      "target": "node_external_repos/repo_beta/.ai/STATE",
      "type": "nesting"
    },
    {
      "source": "node_TEMP",
      "target": "node_TEMP/test_projects",
      "type": "nesting"
    },
    {
      "source": "node_TEMP/test_projects",
      "target": "node_TEMP/test_projects/test_node",
      "type": "nesting"
    },
    {
      "source": "node_TEMP/test_projects",
      "target": "node_TEMP/test_projects/test_py",
      "type": "nesting"
    },
    {
      "source": "node_TEMP/test_projects/test_py",
      "target": "node_TEMP/test_projects/test_py/.ai",
      "type": "nesting"
    },
    {
      "source": "node_TEMP/test_projects/test_py",
      "target": "node_TEMP/test_projects/test_py/src",
      "type": "nesting"
    },
    {
      "source": "node_TEMP/test_projects/test_py",
      "target": "node_TEMP/test_projects/test_py/tests",
      "type": "nesting"
    }
  ]
}